imenu/console.py
imenu/imenu.py
imenu/imenu_builder.py
imenu/skel.py
iMenu-0.2.dist-info/METADATA
iMenu-0.2.dist-info/WHEEL
iMenu-0.2.dist-info/top_level.txt
iMenu-0.2.dist-info/RECORD
