Metadata-Version: 2.1
Name: iMenu
Version: 0.2
Summary: A tiny framework to help create interactive menus on command line
Home-page: https://github.com/rmonico/imenu
Author: Rafael Monico
Author-email: rmonico1@gmail.com
License: GPL3
Platform: UNKNOWN
